[
  {
    "idx": 1211,
    "id": "n1-vocab_reading-1211",
    "target": "交互",
    "sentence": "《交互》の読み方として最もよいものを一つ選びなさい。",
    "options": [
      "こうお",
      "こうご",
      "こうごい",
      "こご"
    ],
    "answer": 1,
    "correct": ""
  },
  {
    "idx": 1212,
    "id": "n1-vocab_reading-1212",
    "target": "工作",
    "sentence": "《工作》の読み方として最もよいものを一つ選びなさい。",
    "options": [
      "こうさくい",
      "こうさお",
      "こうさく",
      "こさく"
    ],
    "answer": 2,
    "correct": ""
  },
  {
    "idx": 1213,
    "id": "n1-vocab_reading-1213",
    "target": "耕作",
    "sentence": "《耕作》の読み方として最もよいものを一つ選びなさい。",
    "options": [
      "こうさくい",
      "こうさお",
      "こさく",
      "こうさく"
    ],
    "answer": 3,
    "correct": ""
  },
  {
    "idx": 1214,
    "id": "n1-vocab_reading-1214",
    "target": "鉱山",
    "sentence": "《鉱山》の読み方として最もよいものを一つ選びなさい。",
    "options": [
      "こうざん",
      "こうざお",
      "こうざんい",
      "こざん"
    ],
    "answer": 0,
    "correct": ""
  },
  {
    "idx": 1215,
    "id": "n1-vocab_reading-1215",
    "target": "講習",
    "sentence": "《講習》の読み方として最もよいものを一つ選びなさい。",
    "options": [
      "こうしゅう",
      "こしゅう",
      "こうしゅうい",
      "こうしゅお"
    ],
    "answer": 0,
    "correct": ""
  },
  {
    "idx": 1216,
    "id": "n1-vocab_reading-1216",
    "target": "交渉",
    "sentence": "《交渉》の読み方として最もよいものを一つ選びなさい。",
    "options": [
      "こうしょう",
      "こしょう",
      "こうしょうい",
      "こうしょお"
    ],
    "answer": 0,
    "correct": ""
  },
  {
    "idx": 1217,
    "id": "n1-vocab_reading-1217",
    "target": "高尚",
    "sentence": "《高尚》の読み方として最もよいものを一つ選びなさい。",
    "options": [
      "こうしょお",
      "こうしょうい",
      "こしょう",
      "こうしょう"
    ],
    "answer": 3,
    "correct": ""
  },
  {
    "idx": 1218,
    "id": "n1-vocab_reading-1218",
    "target": "行進",
    "sentence": "《行進》の読み方として最もよいものを一つ選びなさい。",
    "options": [
      "こうしんい",
      "こしん",
      "こうしん",
      "こうしお"
    ],
    "answer": 2,
    "correct": ""
  },
  {
    "idx": 1219,
    "id": "n1-vocab_reading-1219",
    "target": "香辛料",
    "sentence": "《香辛料》の読み方として最もよいものを一つ選びなさい。",
    "options": [
      "こうしんりょう",
      "こしんりょう",
      "こうしんりょお",
      "こうしんりょうい"
    ],
    "answer": 0,
    "correct": ""
  },
  {
    "idx": 1220,
    "id": "n1-vocab_reading-1220",
    "target": "口述",
    "sentence": "《口述》の読み方として最もよいものを一つ選びなさい。",
    "options": [
      "こうじゅつ",
      "こうしゅつ",
      "こじゅつ",
      "こうじゅつい"
    ],
    "answer": 0,
    "correct": ""
  },
  {
    "idx": 1221,
    "id": "n1-vocab_reading-1221",
    "target": "控除",
    "sentence": "《控除》の読み方として最もよいものを一つ選びなさい。",
    "options": [
      "こうしょ",
      "こじょ",
      "こうじょい",
      "こうじょ"
    ],
    "answer": 3,
    "correct": ""
  },
  {
    "idx": 1222,
    "id": "n1-vocab_reading-1222",
    "target": "向上",
    "sentence": "《向上》の読み方として最もよいものを一つ選びなさい。",
    "options": [
      "こうじょうい",
      "こうしょう",
      "こじょう",
      "こうじょう"
    ],
    "answer": 3,
    "correct": ""
  },
  {
    "idx": 1223,
    "id": "n1-vocab_reading-1223",
    "target": "降水",
    "sentence": "《降水》の読み方として最もよいものを一つ選びなさい。",
    "options": [
      "こうすい",
      "こすい",
      "こうすお",
      "こうすいい"
    ],
    "answer": 0,
    "correct": ""
  },
  {
    "idx": 1224,
    "id": "n1-vocab_reading-1224",
    "target": "洪水",
    "sentence": "《洪水》の読み方として最もよいものを一つ選びなさい。",
    "options": [
      "こずい",
      "こうずい",
      "こうずお",
      "こうずいい"
    ],
    "answer": 1,
    "correct": ""
  },
  {
    "idx": 1225,
    "id": "n1-vocab_reading-1225",
    "target": "公然",
    "sentence": "《公然》の読み方として最もよいものを一つ選びなさい。",
    "options": [
      "こうぜん",
      "こぜん",
      "こうぜんい",
      "こうぜお"
    ],
    "answer": 0,
    "correct": ""
  },
  {
    "idx": 1226,
    "id": "n1-vocab_reading-1226",
    "target": "抗争",
    "sentence": "《抗争》の読み方として最もよいものを一つ選びなさい。",
    "options": [
      "こうそうい",
      "こそう",
      "こうそう",
      "こうそお"
    ],
    "answer": 2,
    "correct": ""
  },
  {
    "idx": 1227,
    "id": "n1-vocab_reading-1227",
    "target": "構想",
    "sentence": "《構想》の読み方として最もよいものを一つ選びなさい。",
    "options": [
      "こうそうい",
      "こうそう",
      "こうそお",
      "こそう"
    ],
    "answer": 1,
    "correct": ""
  },
  {
    "idx": 1228,
    "id": "n1-vocab_reading-1228",
    "target": "拘束",
    "sentence": "《拘束》の読み方として最もよいものを一つ選びなさい。",
    "options": [
      "こうそく",
      "こうそお",
      "こそく",
      "こうそくい"
    ],
    "answer": 0,
    "correct": ""
  },
  {
    "idx": 1229,
    "id": "n1-vocab_reading-1229",
    "target": "公団",
    "sentence": "《公団》の読み方として最もよいものを一つ選びなさい。",
    "options": [
      "こうだお",
      "こうだんい",
      "こだん",
      "こうだん"
    ],
    "answer": 3,
    "correct": ""
  },
  {
    "idx": 1230,
    "id": "n1-vocab_reading-1230",
    "target": "好調",
    "sentence": "《好調》の読み方として最もよいものを一つ選びなさい。",
    "options": [
      "こうちょう",
      "こちょう",
      "こうちょうい",
      "こうちょお"
    ],
    "answer": 0,
    "correct": ""
  },
  {
    "idx": 1231,
    "id": "n1-vocab_reading-1231",
    "target": "講読",
    "sentence": "《講読》の読み方として最もよいものを一つ選びなさい。",
    "options": [
      "こうどく",
      "こどく",
      "こうどお",
      "こうどくい"
    ],
    "answer": 0,
    "correct": ""
  },
  {
    "idx": 1232,
    "id": "n1-vocab_reading-1232",
    "target": "購読",
    "sentence": "《購読》の読み方として最もよいものを一つ選びなさい。",
    "options": [
      "こうどくい",
      "こうどく",
      "こうどお",
      "こどく"
    ],
    "answer": 1,
    "correct": ""
  },
  {
    "idx": 1233,
    "id": "n1-vocab_reading-1233",
    "target": "購入",
    "sentence": "《購入》の読み方として最もよいものを一つ選びなさい。",
    "options": [
      "こうにゅう",
      "こにゅう",
      "こうにゅうい",
      "こうにゅお"
    ],
    "answer": 0,
    "correct": ""
  },
  {
    "idx": 1234,
    "id": "n1-vocab_reading-1234",
    "target": "公認",
    "sentence": "《公認》の読み方として最もよいものを一つ選びなさい。",
    "options": [
      "こにん",
      "こうにん",
      "こうにんい",
      "こうにお"
    ],
    "answer": 1,
    "correct": ""
  },
  {
    "idx": 1235,
    "id": "n1-vocab_reading-1235",
    "target": "荒廃",
    "sentence": "《荒廃》の読み方として最もよいものを一つ選びなさい。",
    "options": [
      "こうはいい",
      "こはい",
      "こうはお",
      "こうはい"
    ],
    "answer": 3,
    "correct": ""
  },
  {
    "idx": 1236,
    "id": "n1-vocab_reading-1236",
    "target": "購買",
    "sentence": "《購買》の読み方として最もよいものを一つ選びなさい。",
    "options": [
      "こうばいい",
      "こばい",
      "こうばい",
      "こうはい"
    ],
    "answer": 2,
    "correct": ""
  },
  {
    "idx": 1237,
    "id": "n1-vocab_reading-1237",
    "target": "好評",
    "sentence": "《好評》の読み方として最もよいものを一つ選びなさい。",
    "options": [
      "こうひょお",
      "こうひょうい",
      "こひょう",
      "こうひょう"
    ],
    "answer": 3,
    "correct": ""
  },
  {
    "idx": 1238,
    "id": "n1-vocab_reading-1238",
    "target": "交付",
    "sentence": "《交付》の読み方として最もよいものを一つ選びなさい。",
    "options": [
      "こふ",
      "こうふ",
      "こうお",
      "こうふい"
    ],
    "answer": 1,
    "correct": ""
  },
  {
    "idx": 1239,
    "id": "n1-vocab_reading-1239",
    "target": "降伏",
    "sentence": "《降伏》の読み方として最もよいものを一つ選びなさい。",
    "options": [
      "こふく",
      "こうふお",
      "こうふく",
      "こうふくい"
    ],
    "answer": 2,
    "correct": ""
  },
  {
    "idx": 1240,
    "id": "n1-vocab_reading-1240",
    "target": "興奮",
    "sentence": "《興奮》の読み方として最もよいものを一つ選びなさい。",
    "options": [
      "こうふんい",
      "こふん",
      "こうふお",
      "こうふん"
    ],
    "answer": 3,
    "correct": ""
  },
  {
    "idx": 1241,
    "id": "n1-vocab_reading-1241",
    "target": "公募",
    "sentence": "《公募》の読み方として最もよいものを一つ選びなさい。",
    "options": [
      "こぼ",
      "こうぼ",
      "こうぼい",
      "こうお"
    ],
    "answer": 1,
    "correct": ""
  },
  {
    "idx": 1242,
    "id": "n1-vocab_reading-1242",
    "target": "巧妙",
    "sentence": "《巧妙》の読み方として最もよいものを一つ選びなさい。",
    "options": [
      "こうみょお",
      "こうみょうい",
      "こみょう",
      "こうみょう"
    ],
    "answer": 3,
    "correct": ""
  },
  {
    "idx": 1243,
    "id": "n1-vocab_reading-1243",
    "target": "公用",
    "sentence": "《公用》の読み方として最もよいものを一つ選びなさい。",
    "options": [
      "こうよお",
      "こうようい",
      "こよう",
      "こうよう"
    ],
    "answer": 3,
    "correct": ""
  },
  {
    "idx": 1244,
    "id": "n1-vocab_reading-1244",
    "target": "小売",
    "sentence": "《小売》の読み方として最もよいものを一つ選びなさい。",
    "options": [
      "こうお",
      "こうりい",
      "こり",
      "こうり"
    ],
    "answer": 3,
    "correct": ""
  },
  {
    "idx": 1245,
    "id": "n1-vocab_reading-1245",
    "target": "効率",
    "sentence": "《効率》の読み方として最もよいものを一つ選びなさい。",
    "options": [
      "こうりつ",
      "こりつ",
      "こうりつい",
      "こうりお"
    ],
    "answer": 0,
    "correct": ""
  },
  {
    "idx": 1246,
    "id": "n1-vocab_reading-1246",
    "target": "公立",
    "sentence": "《公立》の読み方として最もよいものを一つ選びなさい。",
    "options": [
      "こうりお",
      "こうりつい",
      "こりつ",
      "こうりつ"
    ],
    "answer": 3,
    "correct": ""
  },
  {
    "idx": 1247,
    "id": "n1-vocab_reading-1247",
    "target": "小柄",
    "sentence": "《小柄》の読み方として最もよいものを一つ選びなさい。",
    "options": [
      "あああ",
      "こがお",
      "こがらい",
      "こがら"
    ],
    "answer": 3,
    "correct": ""
  },
  {
    "idx": 1248,
    "id": "n1-vocab_reading-1248",
    "target": "小切手",
    "sentence": "《小切手》の読み方として最もよいものを一つ選びなさい。",
    "options": [
      "こぎっお",
      "こぎって",
      "こぎて",
      "こぎってい"
    ],
    "answer": 1,
    "correct": ""
  },
  {
    "idx": 1249,
    "id": "n1-vocab_reading-1249",
    "target": "国産",
    "sentence": "《国産》の読み方として最もよいものを一つ選びなさい。",
    "options": [
      "こくさんい",
      "あああ",
      "こくさん",
      "こくさお"
    ],
    "answer": 2,
    "correct": ""
  },
  {
    "idx": 1250,
    "id": "n1-vocab_reading-1250",
    "target": "国定",
    "sentence": "《国定》の読み方として最もよいものを一つ選びなさい。",
    "options": [
      "あああ",
      "こくてお",
      "こくていい",
      "こくてい"
    ],
    "answer": 3,
    "correct": ""
  },
  {
    "idx": 1251,
    "id": "n1-vocab_reading-1251",
    "target": "国土",
    "sentence": "《国土》の読み方として最もよいものを一つ選びなさい。",
    "options": [
      "こくど",
      "こくどい",
      "こくお",
      "あああ"
    ],
    "answer": 0,
    "correct": ""
  },
  {
    "idx": 1252,
    "id": "n1-vocab_reading-1252",
    "target": "国防",
    "sentence": "《国防》の読み方として最もよいものを一つ選びなさい。",
    "options": [
      "こくぼう",
      "こくぼ",
      "こくぼうい",
      "こくぼお"
    ],
    "answer": 0,
    "correct": ""
  },
  {
    "idx": 1253,
    "id": "n1-vocab_reading-1253",
    "target": "国連",
    "sentence": "《国連》の読み方として最もよいものを一つ選びなさい。",
    "options": [
      "こくれんい",
      "こくれん",
      "あああ",
      "こくれお"
    ],
    "answer": 1,
    "correct": ""
  },
  {
    "idx": 1254,
    "id": "n1-vocab_reading-1254",
    "target": "焦げ茶",
    "sentence": "《焦げ茶》の読み方として最もよいものを一つ選びなさい。",
    "options": [
      "こげちゃ",
      "こげちゃい",
      "あああ",
      "こげちお"
    ],
    "answer": 0,
    "correct": ""
  },
  {
    "idx": 1255,
    "id": "n1-vocab_reading-1255",
    "target": "心地",
    "sentence": "《心地》の読み方として最もよいものを一つ選びなさい。",
    "options": [
      "あああ",
      "ここお",
      "ここちい",
      "ここち"
    ],
    "answer": 3,
    "correct": ""
  },
  {
    "idx": 1256,
    "id": "n1-vocab_reading-1256",
    "target": "心得",
    "sentence": "《心得》の読み方として最もよいものを一つ選びなさい。",
    "options": [
      "あああ",
      "こころえ",
      "こころえい",
      "こころお"
    ],
    "answer": 1,
    "correct": ""
  },
  {
    "idx": 1257,
    "id": "n1-vocab_reading-1257",
    "target": "心掛け",
    "sentence": "《心掛け》の読み方として最もよいものを一つ選びなさい。",
    "options": [
      "こころがお",
      "こころがけ",
      "あああ",
      "こころがけい"
    ],
    "answer": 1,
    "correct": ""
  },
  {
    "idx": 1258,
    "id": "n1-vocab_reading-1258",
    "target": "心掛ける",
    "sentence": "《心掛ける》の読み方として最もよいものを一つ選びなさい。",
    "options": [
      "あああ",
      "こころがけお",
      "こころがけるい",
      "こころがける"
    ],
    "answer": 3,
    "correct": ""
  },
  {
    "idx": 1259,
    "id": "n1-vocab_reading-1259",
    "target": "志",
    "sentence": "《志》の読み方として最もよいものを一つ選びなさい。",
    "options": [
      "こころざしい",
      "こころざお",
      "あああ",
      "こころざし"
    ],
    "answer": 3,
    "correct": ""
  },
  {
    "idx": 1260,
    "id": "n1-vocab_reading-1260",
    "target": "志す",
    "sentence": "《志す》の読み方として最もよいものを一つ選びなさい。",
    "options": [
      "こころざすい",
      "あああ",
      "こころざす",
      "こころざお"
    ],
    "answer": 2,
    "correct": ""
  },
  {
    "idx": 1261,
    "id": "n1-vocab_reading-1261",
    "target": "心強い",
    "sentence": "《心強い》の読み方として最もよいものを一つ選びなさい。",
    "options": [
      "こころづよいい",
      "あああ",
      "こころづよい",
      "こころづよお"
    ],
    "answer": 2,
    "correct": ""
  },
  {
    "idx": 1262,
    "id": "n1-vocab_reading-1262",
    "target": "心細い",
    "sentence": "《心細い》の読み方として最もよいものを一つ選びなさい。",
    "options": [
      "こころぼそい",
      "こころぼそお",
      "こころぼそいい",
      "あああ"
    ],
    "answer": 0,
    "correct": ""
  },
  {
    "idx": 1263,
    "id": "n1-vocab_reading-1263",
    "target": "試み",
    "sentence": "《試み》の読み方として最もよいものを一つ選びなさい。",
    "options": [
      "あああ",
      "こころお",
      "こころみい",
      "こころみ"
    ],
    "answer": 3,
    "correct": ""
  },
  {
    "idx": 1264,
    "id": "n1-vocab_reading-1264",
    "target": "試みる",
    "sentence": "《試みる》の読み方として最もよいものを一つ選びなさい。",
    "options": [
      "こころみる",
      "こころみるい",
      "こころみお",
      "あああ"
    ],
    "answer": 0,
    "correct": ""
  },
  {
    "idx": 1265,
    "id": "n1-vocab_reading-1265",
    "target": "快い",
    "sentence": "《快い》の読み方として最もよいものを一つ選びなさい。",
    "options": [
      "こころよい",
      "こころよいい",
      "こころよお",
      "あああ"
    ],
    "answer": 0,
    "correct": ""
  },
  {
    "idx": 1266,
    "id": "n1-vocab_reading-1266",
    "target": "凝らす",
    "sentence": "《凝らす》の読み方として最もよいものを一つ選びなさい。",
    "options": [
      "あああ",
      "こごらすい",
      "こごらす",
      "こごらお"
    ],
    "answer": 2,
    "correct": ""
  },
  {
    "idx": 1267,
    "id": "n1-vocab_reading-1267",
    "target": "拵える",
    "sentence": "《拵える》の読み方として最もよいものを一つ選びなさい。",
    "options": [
      "あああ",
      "こしらえお",
      "こしらえるい",
      "こしらえる"
    ],
    "answer": 3,
    "correct": ""
  },
  {
    "idx": 1268,
    "id": "n1-vocab_reading-1268",
    "target": "孤児",
    "sentence": "《孤児》の読み方として最もよいものを一つ選びなさい。",
    "options": [
      "こじ",
      "こし",
      "こお",
      "こじい"
    ],
    "answer": 0,
    "correct": ""
  },
  {
    "idx": 1269,
    "id": "n1-vocab_reading-1269",
    "target": "拗れる",
    "sentence": "《拗れる》の読み方として最もよいものを一つ選びなさい。",
    "options": [
      "こじれる",
      "こじれお",
      "こしれる",
      "こじれるい"
    ],
    "answer": 0,
    "correct": ""
  },
  {
    "idx": 1270,
    "id": "n1-vocab_reading-1270",
    "target": "故人",
    "sentence": "《故人》の読み方として最もよいものを一つ選びなさい。",
    "options": [
      "こじん",
      "こしん",
      "こじんい",
      "こじお"
    ],
    "answer": 0,
    "correct": ""
  },
  {
    "idx": 1271,
    "id": "n1-vocab_reading-1271",
    "target": "小銭",
    "sentence": "《小銭》の読み方として最もよいものを一つ選びなさい。",
    "options": [
      "こぜお",
      "こぜに",
      "こぜにい",
      "あああ"
    ],
    "answer": 1,
    "correct": ""
  },
  {
    "idx": 1272,
    "id": "n1-vocab_reading-1272",
    "target": "答え",
    "sentence": "《答え》の読み方として最もよいものを一つ選びなさい。",
    "options": [
      "あああ",
      "こたえ",
      "こたえい",
      "こたお"
    ],
    "answer": 1,
    "correct": ""
  },
  {
    "idx": 1273,
    "id": "n1-vocab_reading-1273",
    "target": "堪える",
    "sentence": "《堪える》の読み方として最もよいものを一つ選びなさい。",
    "options": [
      "こたえお",
      "こたえるい",
      "こたえる",
      "あああ"
    ],
    "answer": 2,
    "correct": ""
  },
  {
    "idx": 1274,
    "id": "n1-vocab_reading-1274",
    "target": "火燵",
    "sentence": "《火燵》の読み方として最もよいものを一つ選びなさい。",
    "options": [
      "あああ",
      "こたお",
      "こたつい",
      "こたつ"
    ],
    "answer": 3,
    "correct": ""
  },
  {
    "idx": 1275,
    "id": "n1-vocab_reading-1275",
    "target": "古代",
    "sentence": "《古代》の読み方として最もよいものを一つ選びなさい。",
    "options": [
      "こだい",
      "あああ",
      "こだお",
      "こだいい"
    ],
    "answer": 0,
    "correct": ""
  },
  {
    "idx": 1276,
    "id": "n1-vocab_reading-1276",
    "target": "拘る",
    "sentence": "《拘る》の読み方として最もよいものを一つ選びなさい。",
    "options": [
      "こだわるい",
      "こだわる",
      "あああ",
      "こだわお"
    ],
    "answer": 1,
    "correct": ""
  },
  {
    "idx": 1277,
    "id": "n1-vocab_reading-1277",
    "target": "誇張",
    "sentence": "《誇張》の読み方として最もよいものを一つ選びなさい。",
    "options": [
      "こちょうい",
      "こちょ",
      "こちょう",
      "こちょお"
    ],
    "answer": 2,
    "correct": ""
  },
  {
    "idx": 1278,
    "id": "n1-vocab_reading-1278",
    "target": "骨",
    "sentence": "《骨》の読み方として最もよいものを一つ選びなさい。",
    "options": [
      "こつい",
      "こつ",
      "あああ",
      "こお"
    ],
    "answer": 1,
    "correct": ""
  },
  {
    "idx": 1279,
    "id": "n1-vocab_reading-1279",
    "target": "固定",
    "sentence": "《固定》の読み方として最もよいものを一つ選びなさい。",
    "options": [
      "こていい",
      "こてお",
      "こてい",
      "あああ"
    ],
    "answer": 2,
    "correct": ""
  },
  {
    "idx": 1280,
    "id": "n1-vocab_reading-1280",
    "target": "事柄",
    "sentence": "《事柄》の読み方として最もよいものを一つ選びなさい。",
    "options": [
      "ことがお",
      "あああ",
      "ことがらい",
      "ことがら"
    ],
    "answer": 3,
    "correct": ""
  },
  {
    "idx": 1281,
    "id": "n1-vocab_reading-1281",
    "target": "悉く",
    "sentence": "《悉く》の読み方として最もよいものを一つ選びなさい。",
    "options": [
      "ことごとく",
      "あああ",
      "ことごとくい",
      "ことごとお"
    ],
    "answer": 0,
    "correct": ""
  },
  {
    "idx": 1282,
    "id": "n1-vocab_reading-1282",
    "target": "言伝",
    "sentence": "《言伝》の読み方として最もよいものを一つ選びなさい。",
    "options": [
      "あああ",
      "ことづお",
      "ことづてい",
      "ことづて"
    ],
    "answer": 3,
    "correct": ""
  },
  {
    "idx": 1283,
    "id": "n1-vocab_reading-1283",
    "target": "殊に",
    "sentence": "《殊に》の読み方として最もよいものを一つ選びなさい。",
    "options": [
      "ことに",
      "ことにい",
      "あああ",
      "ことお"
    ],
    "answer": 0,
    "correct": ""
  },
  {
    "idx": 1284,
    "id": "n1-vocab_reading-1284",
    "target": "事によると",
    "sentence": "《事によると》の読み方として最もよいものを一つ選びなさい。",
    "options": [
      "ことによると",
      "ことによるとい",
      "ことによるお",
      "あああ"
    ],
    "answer": 0,
    "correct": ""
  },
  {
    "idx": 1285,
    "id": "n1-vocab_reading-1285",
    "target": "粉々",
    "sentence": "《粉々》の読み方として最もよいものを一つ選びなさい。",
    "options": [
      "こなごお",
      "こなごない",
      "あああ",
      "こなごな"
    ],
    "answer": 3,
    "correct": ""
  },
  {
    "idx": 1286,
    "id": "n1-vocab_reading-1286",
    "target": "この頃",
    "sentence": "《この頃》の読み方として最もよいものを一つ選びなさい。",
    "options": [
      "このごろ",
      "あああ",
      "このごろい",
      "このごお"
    ],
    "answer": 0,
    "correct": ""
  },
  {
    "idx": 1287,
    "id": "n1-vocab_reading-1287",
    "target": "好ましい",
    "sentence": "《好ましい》の読み方として最もよいものを一つ選びなさい。",
    "options": [
      "このましお",
      "このましいい",
      "あああ",
      "このましい"
    ],
    "answer": 3,
    "correct": ""
  },
  {
    "idx": 1288,
    "id": "n1-vocab_reading-1288",
    "target": "個別",
    "sentence": "《個別》の読み方として最もよいものを一つ選びなさい。",
    "options": [
      "あああ",
      "こべお",
      "こべつい",
      "こべつ"
    ],
    "answer": 3,
    "correct": ""
  },
  {
    "idx": 1289,
    "id": "n1-vocab_reading-1289",
    "target": "細やか",
    "sentence": "《細やか》の読み方として最もよいものを一つ選びなさい。",
    "options": [
      "こまやか",
      "こまやかい",
      "あああ",
      "こまやお"
    ],
    "answer": 0,
    "correct": ""
  },
  {
    "idx": 1290,
    "id": "n1-vocab_reading-1290",
    "target": "込める",
    "sentence": "《込める》の読み方として最もよいものを一つ選びなさい。",
    "options": [
      "こめる",
      "あああ",
      "こめるい",
      "こめお"
    ],
    "answer": 0,
    "correct": ""
  },
  {
    "idx": 1291,
    "id": "n1-vocab_reading-1291",
    "target": "篭る",
    "sentence": "《篭る》の読み方として最もよいものを一つ選びなさい。",
    "options": [
      "あああ",
      "こもる",
      "こもるい",
      "こもお"
    ],
    "answer": 1,
    "correct": ""
  },
  {
    "idx": 1292,
    "id": "n1-vocab_reading-1292",
    "target": "雇用",
    "sentence": "《雇用》の読み方として最もよいものを一つ選びなさい。",
    "options": [
      "こようい",
      "こよう",
      "こよお",
      "こよ"
    ],
    "answer": 1,
    "correct": ""
  },
  {
    "idx": 1293,
    "id": "n1-vocab_reading-1293",
    "target": "暦",
    "sentence": "《暦》の読み方として最もよいものを一つ選びなさい。",
    "options": [
      "こよお",
      "あああ",
      "こよみ",
      "こよみい"
    ],
    "answer": 2,
    "correct": ""
  },
  {
    "idx": 1294,
    "id": "n1-vocab_reading-1294",
    "target": "孤立",
    "sentence": "《孤立》の読み方として最もよいものを一つ選びなさい。",
    "options": [
      "こりつ",
      "こりつい",
      "こりお",
      "あああ"
    ],
    "answer": 0,
    "correct": ""
  },
  {
    "idx": 1295,
    "id": "n1-vocab_reading-1295",
    "target": "懲りる",
    "sentence": "《懲りる》の読み方として最もよいものを一つ選びなさい。",
    "options": [
      "こりお",
      "こりる",
      "こりるい",
      "あああ"
    ],
    "answer": 1,
    "correct": ""
  },
  {
    "idx": 1296,
    "id": "n1-vocab_reading-1296",
    "target": "此れ",
    "sentence": "《此れ》の読み方として最もよいものを一つ選びなさい。",
    "options": [
      "あああ",
      "これ",
      "これい",
      "こお"
    ],
    "answer": 1,
    "correct": ""
  },
  {
    "idx": 1297,
    "id": "n1-vocab_reading-1297",
    "target": "此れ等",
    "sentence": "《此れ等》の読み方として最もよいものを一つ選びなさい。",
    "options": [
      "あああ",
      "これら",
      "これらい",
      "これお"
    ],
    "answer": 1,
    "correct": ""
  },
  {
    "idx": 1298,
    "id": "n1-vocab_reading-1298",
    "target": "魂",
    "sentence": "《魂》の読み方として最もよいものを一つ選びなさい。",
    "options": [
      "こん",
      "こんい",
      "あああ",
      "こお"
    ],
    "answer": 0,
    "correct": ""
  },
  {
    "idx": 1299,
    "id": "n1-vocab_reading-1299",
    "target": "根気",
    "sentence": "《根気》の読み方として最もよいものを一つ選びなさい。",
    "options": [
      "あああ",
      "こんお",
      "こんきい",
      "こんき"
    ],
    "answer": 3,
    "correct": ""
  },
  {
    "idx": 1300,
    "id": "n1-vocab_reading-1300",
    "target": "混血",
    "sentence": "《混血》の読み方として最もよいものを一つ選びなさい。",
    "options": [
      "あああ",
      "こんけお",
      "こんけつい",
      "こんけつ"
    ],
    "answer": 3,
    "correct": ""
  },
  {
    "idx": 1301,
    "id": "n1-vocab_reading-1301",
    "target": "昆虫",
    "sentence": "《昆虫》の読み方として最もよいものを一つ選びなさい。",
    "options": [
      "こんちゅお",
      "こんちゅう",
      "こんちゅうい",
      "こんちゅ"
    ],
    "answer": 1,
    "correct": ""
  },
  {
    "idx": 1302,
    "id": "n1-vocab_reading-1302",
    "target": "混同",
    "sentence": "《混同》の読み方として最もよいものを一つ選びなさい。",
    "options": [
      "こんどお",
      "こんどう",
      "こんど",
      "こんどうい"
    ],
    "answer": 1,
    "correct": ""
  },
  {
    "idx": 1303,
    "id": "n1-vocab_reading-1303",
    "target": "今日は",
    "sentence": "《今日は》の読み方として最もよいものを一つ選びなさい。",
    "options": [
      "こんにちはい",
      "こんにちは",
      "こんにちお",
      "あああ"
    ],
    "answer": 1,
    "correct": ""
  },
  {
    "idx": 1304,
    "id": "n1-vocab_reading-1304",
    "target": "今晩は",
    "sentence": "《今晩は》の読み方として最もよいものを一つ選びなさい。",
    "options": [
      "こんばんお",
      "こんばんは",
      "こんはんは",
      "こんばんはい"
    ],
    "answer": 1,
    "correct": ""
  },
  {
    "idx": 1305,
    "id": "n1-vocab_reading-1305",
    "target": "根本",
    "sentence": "《根本》の読み方として最もよいものを一つ選びなさい。",
    "options": [
      "こんぽん",
      "あああ",
      "こんぽんい",
      "こんぽお"
    ],
    "answer": 0,
    "correct": ""
  },
  {
    "idx": 1306,
    "id": "n1-vocab_reading-1306",
    "target": "御",
    "sentence": "《御》の読み方として最もよいものを一つ選びなさい。",
    "options": [
      "あああ",
      "ごお",
      "ごい",
      "ご"
    ],
    "answer": 3,
    "correct": ""
  },
  {
    "idx": 1307,
    "id": "n1-vocab_reading-1307",
    "target": "語彙",
    "sentence": "《語彙》の読み方として最もよいものを一つ選びなさい。",
    "options": [
      "ごい",
      "ごいい",
      "ごお",
      "あああ"
    ],
    "answer": 0,
    "correct": ""
  },
  {
    "idx": 1308,
    "id": "n1-vocab_reading-1308",
    "target": "濠",
    "sentence": "《濠》の読み方として最もよいものを一つ選びなさい。",
    "options": [
      "ごお",
      "ごうい",
      "ご",
      "ごう"
    ],
    "answer": 3,
    "correct": ""
  },
  {
    "idx": 1309,
    "id": "n1-vocab_reading-1309",
    "target": "業",
    "sentence": "《業》の読み方として最もよいものを一つ選びなさい。",
    "options": [
      "ごう",
      "ごお",
      "ご",
      "ごうい"
    ],
    "answer": 0,
    "correct": ""
  },
  {
    "idx": 1310,
    "id": "n1-vocab_reading-1310",
    "target": "号",
    "sentence": "《号》の読み方として最もよいものを一つ選びなさい。",
    "options": [
      "ごう",
      "ごうい",
      "ごお",
      "ご"
    ],
    "answer": 0,
    "correct": ""
  }
]