[
  {
    "idx": 1811,
    "id": "n1-vocab_reading-1811",
    "target": "絶版",
    "sentence": "《絶版》の読み方として最もよいものを一つ選びなさい。",
    "options": [
      "ぜっぱお",
      "ぜっぱんい",
      "ぜぱん",
      "ぜっぱん"
    ],
    "answer": 3,
    "correct": ""
  },
  {
    "idx": 1812,
    "id": "n1-vocab_reading-1812",
    "target": "絶望",
    "sentence": "《絶望》の読み方として最もよいものを一つ選びなさい。",
    "options": [
      "ぜつぼうい",
      "ぜつぼお",
      "ぜつぼ",
      "ぜつぼう"
    ],
    "answer": 3,
    "correct": ""
  },
  {
    "idx": 1813,
    "id": "n1-vocab_reading-1813",
    "target": "是非とも",
    "sentence": "《是非とも》の読み方として最もよいものを一つ選びなさい。",
    "options": [
      "ぜひとも",
      "ぜひともい",
      "ぜひとお",
      "あああ"
    ],
    "answer": 0,
    "correct": ""
  },
  {
    "idx": 1814,
    "id": "n1-vocab_reading-1814",
    "target": "膳",
    "sentence": "《膳》の読み方として最もよいものを一つ選びなさい。",
    "options": [
      "ぜん",
      "ぜお",
      "あああ",
      "ぜんい"
    ],
    "answer": 0,
    "correct": ""
  },
  {
    "idx": 1815,
    "id": "n1-vocab_reading-1815",
    "target": "禅",
    "sentence": "《禅》の読み方として最もよいものを一つ選びなさい。",
    "options": [
      "ぜん",
      "ぜんい",
      "ぜお",
      "あああ"
    ],
    "answer": 0,
    "correct": ""
  },
  {
    "idx": 1816,
    "id": "n1-vocab_reading-1816",
    "target": "全快",
    "sentence": "《全快》の読み方として最もよいものを一つ選びなさい。",
    "options": [
      "ぜんかい",
      "ぜんかいい",
      "ぜんかお",
      "あああ"
    ],
    "answer": 0,
    "correct": ""
  },
  {
    "idx": 1817,
    "id": "n1-vocab_reading-1817",
    "target": "全盛",
    "sentence": "《全盛》の読み方として最もよいものを一つ選びなさい。",
    "options": [
      "ぜんせい",
      "あああ",
      "ぜんせいい",
      "ぜんせお"
    ],
    "answer": 0,
    "correct": ""
  },
  {
    "idx": 1818,
    "id": "n1-vocab_reading-1818",
    "target": "前提",
    "sentence": "《前提》の読み方として最もよいものを一つ選びなさい。",
    "options": [
      "ぜんてお",
      "ぜんていい",
      "あああ",
      "ぜんてい"
    ],
    "answer": 3,
    "correct": ""
  },
  {
    "idx": 1819,
    "id": "n1-vocab_reading-1819",
    "target": "前途",
    "sentence": "《前途》の読み方として最もよいものを一つ選びなさい。",
    "options": [
      "ぜんと",
      "ぜんとい",
      "あああ",
      "ぜんお"
    ],
    "answer": 0,
    "correct": ""
  },
  {
    "idx": 1820,
    "id": "n1-vocab_reading-1820",
    "target": "善良",
    "sentence": "《善良》の読み方として最もよいものを一つ選びなさい。",
    "options": [
      "ぜんりょ",
      "ぜんりょお",
      "ぜんりょう",
      "ぜんりょうい"
    ],
    "answer": 2,
    "correct": ""
  },
  {
    "idx": 1821,
    "id": "n1-vocab_reading-1821",
    "target": "前例",
    "sentence": "《前例》の読み方として最もよいものを一つ選びなさい。",
    "options": [
      "ぜんれお",
      "ぜんれいい",
      "ぜんれい",
      "あああ"
    ],
    "answer": 2,
    "correct": ""
  },
  {
    "idx": 1822,
    "id": "n1-vocab_reading-1822",
    "target": "僧",
    "sentence": "《僧》の読み方として最もよいものを一つ選びなさい。",
    "options": [
      "そお",
      "そうい",
      "そ",
      "そう"
    ],
    "answer": 3,
    "correct": ""
  },
  {
    "idx": 1823,
    "id": "n1-vocab_reading-1823",
    "target": "沿う",
    "sentence": "《沿う》の読み方として最もよいものを一つ選びなさい。",
    "options": [
      "そ",
      "そう",
      "そうい",
      "そお"
    ],
    "answer": 1,
    "correct": ""
  },
  {
    "idx": 1824,
    "id": "n1-vocab_reading-1824",
    "target": "添う",
    "sentence": "《添う》の読み方として最もよいものを一つ選びなさい。",
    "options": [
      "そ",
      "そうい",
      "そお",
      "そう"
    ],
    "answer": 3,
    "correct": ""
  },
  {
    "idx": 1825,
    "id": "n1-vocab_reading-1825",
    "target": "総",
    "sentence": "《総》の読み方として最もよいものを一つ選びなさい。",
    "options": [
      "そう",
      "そうい",
      "そ",
      "そお"
    ],
    "answer": 0,
    "correct": ""
  },
  {
    "idx": 1826,
    "id": "n1-vocab_reading-1826",
    "target": "相応",
    "sentence": "《相応》の読み方として最もよいものを一つ選びなさい。",
    "options": [
      "そおう",
      "そうおう",
      "そうおうい",
      "そうおお"
    ],
    "answer": 1,
    "correct": ""
  },
  {
    "idx": 1827,
    "id": "n1-vocab_reading-1827",
    "target": "総会",
    "sentence": "《総会》の読み方として最もよいものを一つ選びなさい。",
    "options": [
      "そうかいい",
      "そうかい",
      "そうかお",
      "そかい"
    ],
    "answer": 1,
    "correct": ""
  },
  {
    "idx": 1828,
    "id": "n1-vocab_reading-1828",
    "target": "送金",
    "sentence": "《送金》の読み方として最もよいものを一つ選びなさい。",
    "options": [
      "そうきん",
      "そうきんい",
      "そきん",
      "そうきお"
    ],
    "answer": 0,
    "correct": ""
  },
  {
    "idx": 1829,
    "id": "n1-vocab_reading-1829",
    "target": "走行",
    "sentence": "《走行》の読み方として最もよいものを一つ選びなさい。",
    "options": [
      "そこう",
      "そうこうい",
      "そうこお",
      "そうこう"
    ],
    "answer": 3,
    "correct": ""
  },
  {
    "idx": 1830,
    "id": "n1-vocab_reading-1830",
    "target": "捜索",
    "sentence": "《捜索》の読み方として最もよいものを一つ選びなさい。",
    "options": [
      "そうさく",
      "そさく",
      "そうさくい",
      "そうさお"
    ],
    "answer": 0,
    "correct": ""
  },
  {
    "idx": 1831,
    "id": "n1-vocab_reading-1831",
    "target": "然うして",
    "sentence": "《然うして》の読み方として最もよいものを一つ選びなさい。",
    "options": [
      "そして",
      "そうして",
      "そうしてい",
      "そうしお"
    ],
    "answer": 1,
    "correct": ""
  },
  {
    "idx": 1832,
    "id": "n1-vocab_reading-1832",
    "target": "装飾",
    "sentence": "《装飾》の読み方として最もよいものを一つ選びなさい。",
    "options": [
      "そうしょくい",
      "そしょく",
      "そうしょく",
      "そうしょお"
    ],
    "answer": 2,
    "correct": ""
  },
  {
    "idx": 1833,
    "id": "n1-vocab_reading-1833",
    "target": "操縦",
    "sentence": "《操縦》の読み方として最もよいものを一つ選びなさい。",
    "options": [
      "そうじゅうい",
      "そうしゅう",
      "そじゅう",
      "そうじゅう"
    ],
    "answer": 3,
    "correct": ""
  },
  {
    "idx": 1834,
    "id": "n1-vocab_reading-1834",
    "target": "創造",
    "sentence": "《創造》の読み方として最もよいものを一つ選びなさい。",
    "options": [
      "そうぞうい",
      "そうぞお",
      "そぞう",
      "そうぞう"
    ],
    "answer": 3,
    "correct": ""
  },
  {
    "idx": 1835,
    "id": "n1-vocab_reading-1835",
    "target": "壮大",
    "sentence": "《壮大》の読み方として最もよいものを一つ選びなさい。",
    "options": [
      "そだい",
      "そうだいい",
      "そうだい",
      "そうだお"
    ],
    "answer": 2,
    "correct": ""
  },
  {
    "idx": 1836,
    "id": "n1-vocab_reading-1836",
    "target": "騒動",
    "sentence": "《騒動》の読み方として最もよいものを一つ選びなさい。",
    "options": [
      "そうどお",
      "そうどうい",
      "そどう",
      "そうどう"
    ],
    "answer": 3,
    "correct": ""
  },
  {
    "idx": 1837,
    "id": "n1-vocab_reading-1837",
    "target": "遭難",
    "sentence": "《遭難》の読み方として最もよいものを一つ選びなさい。",
    "options": [
      "そうなお",
      "そうなんい",
      "そなん",
      "そうなん"
    ],
    "answer": 3,
    "correct": ""
  },
  {
    "idx": 1838,
    "id": "n1-vocab_reading-1838",
    "target": "相場",
    "sentence": "《相場》の読み方として最もよいものを一つ選びなさい。",
    "options": [
      "そば",
      "そうばい",
      "そうは",
      "そうば"
    ],
    "answer": 3,
    "correct": ""
  },
  {
    "idx": 1839,
    "id": "n1-vocab_reading-1839",
    "target": "装備",
    "sentence": "《装備》の読み方として最もよいものを一つ選びなさい。",
    "options": [
      "そうお",
      "そび",
      "そうび",
      "そうびい"
    ],
    "answer": 2,
    "correct": ""
  },
  {
    "idx": 1840,
    "id": "n1-vocab_reading-1840",
    "target": "創立",
    "sentence": "《創立》の読み方として最もよいものを一つ選びなさい。",
    "options": [
      "そりつ",
      "そうりつ",
      "そうりつい",
      "そうりお"
    ],
    "answer": 1,
    "correct": ""
  },
  {
    "idx": 1841,
    "id": "n1-vocab_reading-1841",
    "target": "添える",
    "sentence": "《添える》の読み方として最もよいものを一つ選びなさい。",
    "options": [
      "あああ",
      "そえるい",
      "そえる",
      "そえお"
    ],
    "answer": 2,
    "correct": ""
  },
  {
    "idx": 1842,
    "id": "n1-vocab_reading-1842",
    "target": "即座に",
    "sentence": "《即座に》の読み方として最もよいものを一つ選びなさい。",
    "options": [
      "あああ",
      "そくざお",
      "そくざにい",
      "そくざに"
    ],
    "answer": 3,
    "correct": ""
  },
  {
    "idx": 1843,
    "id": "n1-vocab_reading-1843",
    "target": "即する",
    "sentence": "《即する》の読み方として最もよいものを一つ選びなさい。",
    "options": [
      "そくすお",
      "そくするい",
      "あああ",
      "そくする"
    ],
    "answer": 3,
    "correct": ""
  },
  {
    "idx": 1844,
    "id": "n1-vocab_reading-1844",
    "target": "側面",
    "sentence": "《側面》の読み方として最もよいものを一つ選びなさい。",
    "options": [
      "そくめん",
      "そくめんい",
      "あああ",
      "そくめお"
    ],
    "answer": 0,
    "correct": ""
  },
  {
    "idx": 1845,
    "id": "n1-vocab_reading-1845",
    "target": "其処で",
    "sentence": "《其処で》の読み方として最もよいものを一つ選びなさい。",
    "options": [
      "そこでい",
      "あああ",
      "そこお",
      "そこで"
    ],
    "answer": 3,
    "correct": ""
  },
  {
    "idx": 1846,
    "id": "n1-vocab_reading-1846",
    "target": "損なう",
    "sentence": "《損なう》の読み方として最もよいものを一つ選びなさい。",
    "options": [
      "そこなお",
      "そこなうい",
      "そこな",
      "そこなう"
    ],
    "answer": 3,
    "correct": ""
  },
  {
    "idx": 1847,
    "id": "n1-vocab_reading-1847",
    "target": "其処ら",
    "sentence": "《其処ら》の読み方として最もよいものを一つ選びなさい。",
    "options": [
      "あああ",
      "そこお",
      "そこらい",
      "そこら"
    ],
    "answer": 3,
    "correct": ""
  },
  {
    "idx": 1848,
    "id": "n1-vocab_reading-1848",
    "target": "阻止",
    "sentence": "《阻止》の読み方として最もよいものを一つ選びなさい。",
    "options": [
      "そし",
      "そしい",
      "そお",
      "あああ"
    ],
    "answer": 0,
    "correct": ""
  },
  {
    "idx": 1849,
    "id": "n1-vocab_reading-1849",
    "target": "然して",
    "sentence": "《然して》の読み方として最もよいものを一つ選びなさい。",
    "options": [
      "そして",
      "あああ",
      "そしてい",
      "そしお"
    ],
    "answer": 0,
    "correct": ""
  },
  {
    "idx": 1850,
    "id": "n1-vocab_reading-1850",
    "target": "訴訟",
    "sentence": "《訴訟》の読み方として最もよいものを一つ選びなさい。",
    "options": [
      "そしょお",
      "そしょう",
      "そしょ",
      "そしょうい"
    ],
    "answer": 1,
    "correct": ""
  },
  {
    "idx": 1851,
    "id": "n1-vocab_reading-1851",
    "target": "育ち",
    "sentence": "《育ち》の読み方として最もよいものを一つ選びなさい。",
    "options": [
      "そだち",
      "そだちい",
      "そだお",
      "あああ"
    ],
    "answer": 0,
    "correct": ""
  },
  {
    "idx": 1852,
    "id": "n1-vocab_reading-1852",
    "target": "其方",
    "sentence": "《其方》の読み方として最もよいものを一つ選びなさい。",
    "options": [
      "そちお",
      "あああ",
      "そちらい",
      "そちら"
    ],
    "answer": 3,
    "correct": ""
  },
  {
    "idx": 1853,
    "id": "n1-vocab_reading-1853",
    "target": "外方",
    "sentence": "《外方》の読み方として最もよいものを一つ選びなさい。",
    "options": [
      "そっぽい",
      "そぽ",
      "そっぽ",
      "そっお"
    ],
    "answer": 2,
    "correct": ""
  },
  {
    "idx": 1854,
    "id": "n1-vocab_reading-1854",
    "target": "備え付ける",
    "sentence": "《備え付ける》の読み方として最もよいものを一つ選びなさい。",
    "options": [
      "あああ",
      "そなえつける",
      "そなえつけるい",
      "そなえつけお"
    ],
    "answer": 1,
    "correct": ""
  },
  {
    "idx": 1855,
    "id": "n1-vocab_reading-1855",
    "target": "備わる",
    "sentence": "《備わる》の読み方として最もよいものを一つ選びなさい。",
    "options": [
      "あああ",
      "そなわる",
      "そなわるい",
      "そなわお"
    ],
    "answer": 1,
    "correct": ""
  },
  {
    "idx": 1856,
    "id": "n1-vocab_reading-1856",
    "target": "その上",
    "sentence": "《その上》の読み方として最もよいものを一つ選びなさい。",
    "options": [
      "そのうえ",
      "そのえ",
      "そのうお",
      "そのうえい"
    ],
    "answer": 0,
    "correct": ""
  },
  {
    "idx": 1857,
    "id": "n1-vocab_reading-1857",
    "target": "その内",
    "sentence": "《その内》の読み方として最もよいものを一つ選びなさい。",
    "options": [
      "そのうち",
      "そのち",
      "そのうお",
      "そのうちい"
    ],
    "answer": 0,
    "correct": ""
  },
  {
    "idx": 1858,
    "id": "n1-vocab_reading-1858",
    "target": "その外",
    "sentence": "《その外》の読み方として最もよいものを一つ選びなさい。",
    "options": [
      "あああ",
      "そのほかい",
      "そのほか",
      "そのほお"
    ],
    "answer": 2,
    "correct": ""
  },
  {
    "idx": 1859,
    "id": "n1-vocab_reading-1859",
    "target": "其の儘",
    "sentence": "《其の儘》の読み方として最もよいものを一つ選びなさい。",
    "options": [
      "そのまま",
      "そのままい",
      "そのまお",
      "あああ"
    ],
    "answer": 0,
    "correct": ""
  },
  {
    "idx": 1860,
    "id": "n1-vocab_reading-1860",
    "target": "聳える",
    "sentence": "《聳える》の読み方として最もよいものを一つ選びなさい。",
    "options": [
      "そびえる",
      "そびえるい",
      "そびえお",
      "あああ"
    ],
    "answer": 0,
    "correct": ""
  },
  {
    "idx": 1861,
    "id": "n1-vocab_reading-1861",
    "target": "素朴",
    "sentence": "《素朴》の読み方として最もよいものを一つ選びなさい。",
    "options": [
      "そぼお",
      "あああ",
      "そぼくい",
      "そぼく"
    ],
    "answer": 3,
    "correct": ""
  },
  {
    "idx": 1862,
    "id": "n1-vocab_reading-1862",
    "target": "染まる",
    "sentence": "《染まる》の読み方として最もよいものを一つ選びなさい。",
    "options": [
      "あああ",
      "そまお",
      "そまるい",
      "そまる"
    ],
    "answer": 3,
    "correct": ""
  },
  {
    "idx": 1863,
    "id": "n1-vocab_reading-1863",
    "target": "背く",
    "sentence": "《背く》の読み方として最もよいものを一つ選びなさい。",
    "options": [
      "あああ",
      "そむく",
      "そむくい",
      "そむお"
    ],
    "answer": 1,
    "correct": ""
  },
  {
    "idx": 1864,
    "id": "n1-vocab_reading-1864",
    "target": "逸らす",
    "sentence": "《逸らす》の読み方として最もよいものを一つ選びなさい。",
    "options": [
      "そらす",
      "そらすい",
      "そらお",
      "あああ"
    ],
    "answer": 0,
    "correct": ""
  },
  {
    "idx": 1865,
    "id": "n1-vocab_reading-1865",
    "target": "反り",
    "sentence": "《反り》の読み方として最もよいものを一つ選びなさい。",
    "options": [
      "そり",
      "そりい",
      "そお",
      "あああ"
    ],
    "answer": 0,
    "correct": ""
  },
  {
    "idx": 1866,
    "id": "n1-vocab_reading-1866",
    "target": "其れ",
    "sentence": "《其れ》の読み方として最もよいものを一つ選びなさい。",
    "options": [
      "あああ",
      "それ",
      "それい",
      "そお"
    ],
    "answer": 1,
    "correct": ""
  },
  {
    "idx": 1867,
    "id": "n1-vocab_reading-1867",
    "target": "其れから",
    "sentence": "《其れから》の読み方として最もよいものを一つ選びなさい。",
    "options": [
      "それから",
      "それからい",
      "それかお",
      "あああ"
    ],
    "answer": 0,
    "correct": ""
  },
  {
    "idx": 1868,
    "id": "n1-vocab_reading-1868",
    "target": "其れで",
    "sentence": "《其れで》の読み方として最もよいものを一つ選びなさい。",
    "options": [
      "あああ",
      "それお",
      "それでい",
      "それで"
    ],
    "answer": 3,
    "correct": ""
  },
  {
    "idx": 1869,
    "id": "n1-vocab_reading-1869",
    "target": "其れでも",
    "sentence": "《其れでも》の読み方として最もよいものを一つ選びなさい。",
    "options": [
      "あああ",
      "それでお",
      "それでもい",
      "それでも"
    ],
    "answer": 3,
    "correct": ""
  },
  {
    "idx": 1870,
    "id": "n1-vocab_reading-1870",
    "target": "其れとも",
    "sentence": "《其れとも》の読み方として最もよいものを一つ選びなさい。",
    "options": [
      "それとお",
      "それともい",
      "あああ",
      "それとも"
    ],
    "answer": 3,
    "correct": ""
  },
  {
    "idx": 1871,
    "id": "n1-vocab_reading-1871",
    "target": "其れに",
    "sentence": "《其れに》の読み方として最もよいものを一つ選びなさい。",
    "options": [
      "それに",
      "それにい",
      "それお",
      "あああ"
    ],
    "answer": 0,
    "correct": ""
  },
  {
    "idx": 1872,
    "id": "n1-vocab_reading-1872",
    "target": "其れ故",
    "sentence": "《其れ故》の読み方として最もよいものを一つ選びなさい。",
    "options": [
      "あああ",
      "それゆえい",
      "それゆえ",
      "それゆお"
    ],
    "answer": 2,
    "correct": ""
  },
  {
    "idx": 1873,
    "id": "n1-vocab_reading-1873",
    "target": "揃い",
    "sentence": "《揃い》の読み方として最もよいものを一つ選びなさい。",
    "options": [
      "そろい",
      "そろいい",
      "あああ",
      "そろお"
    ],
    "answer": 0,
    "correct": ""
  },
  {
    "idx": 1874,
    "id": "n1-vocab_reading-1874",
    "target": "損失",
    "sentence": "《損失》の読み方として最もよいものを一つ選びなさい。",
    "options": [
      "そんしつい",
      "あああ",
      "そんしつ",
      "そんしお"
    ],
    "answer": 2,
    "correct": ""
  },
  {
    "idx": 1875,
    "id": "n1-vocab_reading-1875",
    "target": "存続",
    "sentence": "《存続》の読み方として最もよいものを一つ選びなさい。",
    "options": [
      "そんぞくい",
      "あああ",
      "そんぞお",
      "そんぞく"
    ],
    "answer": 3,
    "correct": ""
  },
  {
    "idx": 1876,
    "id": "n1-vocab_reading-1876",
    "target": "沿い",
    "sentence": "《沿い》の読み方として最もよいものを一つ選びなさい。",
    "options": [
      "あああ",
      "ぞお",
      "ぞいい",
      "ぞい"
    ],
    "answer": 3,
    "correct": ""
  },
  {
    "idx": 1877,
    "id": "n1-vocab_reading-1877",
    "target": "増強",
    "sentence": "《増強》の読み方として最もよいものを一つ選びなさい。",
    "options": [
      "ぞうきょう",
      "ぞうきょお",
      "ぞうきょうい",
      "ぞきょう"
    ],
    "answer": 0,
    "correct": ""
  },
  {
    "idx": 1878,
    "id": "n1-vocab_reading-1878",
    "target": "蔵相",
    "sentence": "《蔵相》の読み方として最もよいものを一つ選びなさい。",
    "options": [
      "ぞうしょお",
      "ぞうしょうい",
      "ぞしょう",
      "ぞうしょう"
    ],
    "answer": 3,
    "correct": ""
  },
  {
    "idx": 1879,
    "id": "n1-vocab_reading-1879",
    "target": "増進",
    "sentence": "《増進》の読み方として最もよいものを一つ選びなさい。",
    "options": [
      "ぞしん",
      "ぞうしん",
      "ぞうしんい",
      "ぞうしお"
    ],
    "answer": 1,
    "correct": ""
  },
  {
    "idx": 1880,
    "id": "n1-vocab_reading-1880",
    "target": "他意",
    "sentence": "《他意》の読み方として最もよいものを一つ選びなさい。",
    "options": [
      "たい",
      "たお",
      "あああ",
      "たいい"
    ],
    "answer": 0,
    "correct": ""
  },
  {
    "idx": 1881,
    "id": "n1-vocab_reading-1881",
    "target": "体格",
    "sentence": "《体格》の読み方として最もよいものを一つ選びなさい。",
    "options": [
      "たいかお",
      "たいかくい",
      "あああ",
      "たいかく"
    ],
    "answer": 3,
    "correct": ""
  },
  {
    "idx": 1882,
    "id": "n1-vocab_reading-1882",
    "target": "大概",
    "sentence": "《大概》の読み方として最もよいものを一つ選びなさい。",
    "options": [
      "たいがお",
      "あああ",
      "たいがいい",
      "たいがい"
    ],
    "answer": 3,
    "correct": ""
  },
  {
    "idx": 1883,
    "id": "n1-vocab_reading-1883",
    "target": "退学",
    "sentence": "《退学》の読み方として最もよいものを一つ選びなさい。",
    "options": [
      "たいがく",
      "たいがくい",
      "たいがお",
      "あああ"
    ],
    "answer": 0,
    "correct": ""
  },
  {
    "idx": 1884,
    "id": "n1-vocab_reading-1884",
    "target": "大金",
    "sentence": "《大金》の読み方として最もよいものを一つ選びなさい。",
    "options": [
      "あああ",
      "たいきお",
      "たいきんい",
      "たいきん"
    ],
    "answer": 3,
    "correct": ""
  },
  {
    "idx": 1885,
    "id": "n1-vocab_reading-1885",
    "target": "対決",
    "sentence": "《対決》の読み方として最もよいものを一つ選びなさい。",
    "options": [
      "たいけつ",
      "たいけつい",
      "たいけお",
      "あああ"
    ],
    "answer": 0,
    "correct": ""
  },
  {
    "idx": 1886,
    "id": "n1-vocab_reading-1886",
    "target": "体験",
    "sentence": "《体験》の読み方として最もよいものを一つ選びなさい。",
    "options": [
      "たいけお",
      "たいけんい",
      "たいけん",
      "あああ"
    ],
    "answer": 2,
    "correct": ""
  },
  {
    "idx": 1887,
    "id": "n1-vocab_reading-1887",
    "target": "対抗",
    "sentence": "《対抗》の読み方として最もよいものを一つ選びなさい。",
    "options": [
      "たいこ",
      "たいこう",
      "たいこうい",
      "たいこお"
    ],
    "answer": 1,
    "correct": ""
  },
  {
    "idx": 1888,
    "id": "n1-vocab_reading-1888",
    "target": "対して",
    "sentence": "《対して》の読み方として最もよいものを一つ選びなさい。",
    "options": [
      "たいしお",
      "たいしてい",
      "あああ",
      "たいして"
    ],
    "answer": 3,
    "correct": ""
  },
  {
    "idx": 1889,
    "id": "n1-vocab_reading-1889",
    "target": "大衆",
    "sentence": "《大衆》の読み方として最もよいものを一つ選びなさい。",
    "options": [
      "たいしゅう",
      "たいしゅ",
      "たいしゅうい",
      "たいしゅお"
    ],
    "answer": 0,
    "correct": ""
  },
  {
    "idx": 1890,
    "id": "n1-vocab_reading-1890",
    "target": "対処",
    "sentence": "《対処》の読み方として最もよいものを一つ選びなさい。",
    "options": [
      "たいしょい",
      "たいしょ",
      "あああ",
      "たいしお"
    ],
    "answer": 1,
    "correct": ""
  },
  {
    "idx": 1891,
    "id": "n1-vocab_reading-1891",
    "target": "退職",
    "sentence": "《退職》の読み方として最もよいものを一つ選びなさい。",
    "options": [
      "あああ",
      "たいしょく",
      "たいしょくい",
      "たいしょお"
    ],
    "answer": 1,
    "correct": ""
  },
  {
    "idx": 1892,
    "id": "n1-vocab_reading-1892",
    "target": "退治",
    "sentence": "《退治》の読み方として最もよいものを一つ選びなさい。",
    "options": [
      "たいお",
      "たいじ",
      "たいし",
      "たいじい"
    ],
    "answer": 1,
    "correct": ""
  },
  {
    "idx": 1893,
    "id": "n1-vocab_reading-1893",
    "target": "態勢",
    "sentence": "《態勢》の読み方として最もよいものを一つ選びなさい。",
    "options": [
      "たいせい",
      "あああ",
      "たいせいい",
      "たいせお"
    ],
    "answer": 0,
    "correct": ""
  },
  {
    "idx": 1894,
    "id": "n1-vocab_reading-1894",
    "target": "対談",
    "sentence": "《対談》の読み方として最もよいものを一つ選びなさい。",
    "options": [
      "たいだん",
      "たいだんい",
      "たいだお",
      "あああ"
    ],
    "answer": 0,
    "correct": ""
  },
  {
    "idx": 1895,
    "id": "n1-vocab_reading-1895",
    "target": "対等",
    "sentence": "《対等》の読み方として最もよいものを一つ選びなさい。",
    "options": [
      "たいとお",
      "たいとうい",
      "たいと",
      "たいとう"
    ],
    "answer": 3,
    "correct": ""
  },
  {
    "idx": 1896,
    "id": "n1-vocab_reading-1896",
    "target": "滞納",
    "sentence": "《滞納》の読み方として最もよいものを一つ選びなさい。",
    "options": [
      "たいのお",
      "たいのう",
      "たいの",
      "たいのうい"
    ],
    "answer": 1,
    "correct": ""
  },
  {
    "idx": 1897,
    "id": "n1-vocab_reading-1897",
    "target": "対比",
    "sentence": "《対比》の読み方として最もよいものを一つ選びなさい。",
    "options": [
      "あああ",
      "たいお",
      "たいひい",
      "たいひ"
    ],
    "answer": 3,
    "correct": ""
  },
  {
    "idx": 1898,
    "id": "n1-vocab_reading-1898",
    "target": "対辺",
    "sentence": "《対辺》の読み方として最もよいものを一つ選びなさい。",
    "options": [
      "あああ",
      "たいへお",
      "たいへんい",
      "たいへん"
    ],
    "answer": 3,
    "correct": ""
  },
  {
    "idx": 1899,
    "id": "n1-vocab_reading-1899",
    "target": "待望",
    "sentence": "《待望》の読み方として最もよいものを一つ選びなさい。",
    "options": [
      "たいぼお",
      "たいぼうい",
      "たいぼ",
      "たいぼう"
    ],
    "answer": 3,
    "correct": ""
  },
  {
    "idx": 1900,
    "id": "n1-vocab_reading-1900",
    "target": "怠慢",
    "sentence": "《怠慢》の読み方として最もよいものを一つ選びなさい。",
    "options": [
      "たいまん",
      "たいまんい",
      "あああ",
      "たいまお"
    ],
    "answer": 0,
    "correct": ""
  },
  {
    "idx": 1901,
    "id": "n1-vocab_reading-1901",
    "target": "対面",
    "sentence": "《対面》の読み方として最もよいものを一つ選びなさい。",
    "options": [
      "あああ",
      "たいめお",
      "たいめんい",
      "たいめん"
    ],
    "answer": 3,
    "correct": ""
  },
  {
    "idx": 1902,
    "id": "n1-vocab_reading-1902",
    "target": "体力",
    "sentence": "《体力》の読み方として最もよいものを一つ選びなさい。",
    "options": [
      "たいりょお",
      "あああ",
      "たいりょくい",
      "たいりょく"
    ],
    "answer": 3,
    "correct": ""
  },
  {
    "idx": 1903,
    "id": "n1-vocab_reading-1903",
    "target": "対話",
    "sentence": "《対話》の読み方として最もよいものを一つ選びなさい。",
    "options": [
      "たいわ",
      "たいわい",
      "あああ",
      "たいお"
    ],
    "answer": 0,
    "correct": ""
  },
  {
    "idx": 1904,
    "id": "n1-vocab_reading-1904",
    "target": "絶える",
    "sentence": "《絶える》の読み方として最もよいものを一つ選びなさい。",
    "options": [
      "あああ",
      "たえお",
      "たえるい",
      "たえる"
    ],
    "answer": 3,
    "correct": ""
  },
  {
    "idx": 1905,
    "id": "n1-vocab_reading-1905",
    "target": "高",
    "sentence": "《高》の読み方として最もよいものを一つ選びなさい。",
    "options": [
      "あああ",
      "たかい",
      "たお",
      "たか"
    ],
    "answer": 3,
    "correct": ""
  },
  {
    "idx": 1906,
    "id": "n1-vocab_reading-1906",
    "target": "高まる",
    "sentence": "《高まる》の読み方として最もよいものを一つ選びなさい。",
    "options": [
      "たかまる",
      "たかまるい",
      "たかまお",
      "あああ"
    ],
    "answer": 0,
    "correct": ""
  },
  {
    "idx": 1907,
    "id": "n1-vocab_reading-1907",
    "target": "焚火",
    "sentence": "《焚火》の読み方として最もよいものを一つ選びなさい。",
    "options": [
      "たきび",
      "たきびい",
      "たきお",
      "あああ"
    ],
    "answer": 0,
    "correct": ""
  },
  {
    "idx": 1908,
    "id": "n1-vocab_reading-1908",
    "target": "沢山",
    "sentence": "《沢山》の読み方として最もよいものを一つ選びなさい。",
    "options": [
      "たくさん",
      "たくさんい",
      "あああ",
      "たくさお"
    ],
    "answer": 0,
    "correct": ""
  },
  {
    "idx": 1909,
    "id": "n1-vocab_reading-1909",
    "target": "逞しい",
    "sentence": "《逞しい》の読み方として最もよいものを一つ選びなさい。",
    "options": [
      "たくましお",
      "あああ",
      "たくましいい",
      "たくましい"
    ],
    "answer": 3,
    "correct": ""
  },
  {
    "idx": 1910,
    "id": "n1-vocab_reading-1910",
    "target": "巧み",
    "sentence": "《巧み》の読み方として最もよいものを一つ選びなさい。",
    "options": [
      "あああ",
      "たくお",
      "たくみい",
      "たくみ"
    ],
    "answer": 3,
    "correct": ""
  }
]