[
  {
    "idx": 11,
    "id": "n5-vocab_reading-011",
    "target": "働く",
    "sentence": "この《働く》の読み方を選んでください。",
    "options": [
      "はたらく",
      "はたらくい",
      "はたらお"
    ],
    "answer": 0,
    "correct": ""
  },
  {
    "idx": 12,
    "id": "n5-vocab_reading-012",
    "target": "着く",
    "sentence": "この《着く》の読み方を選んでください。",
    "options": [
      "つく",
      "つくい",
      "つお"
    ],
    "answer": 0,
    "correct": ""
  },
  {
    "idx": 13,
    "id": "n5-vocab_reading-013",
    "target": "大使館",
    "sentence": "この《大使館》の読み方を選んでください。",
    "options": [
      "たいしかん",
      "たいしかお",
      "たいしかんい"
    ],
    "answer": 0,
    "correct": ""
  },
  {
    "idx": 14,
    "id": "n5-vocab_reading-014",
    "target": "頼む",
    "sentence": "この《頼む》の読み方を選んでください。",
    "options": [
      "たのむい",
      "たのむ",
      "たのお"
    ],
    "answer": 1,
    "correct": ""
  },
  {
    "idx": 15,
    "id": "n5-vocab_reading-015",
    "target": "小さな",
    "sentence": "この《小さな》の読み方を選んでください。",
    "options": [
      "ちいさお",
      "ちいさない",
      "ちいさな"
    ],
    "answer": 2,
    "correct": ""
  },
  {
    "idx": 16,
    "id": "n5-vocab_reading-016",
    "target": "違う",
    "sentence": "この《違う》の読み方を選んでください。",
    "options": [
      "ちがうい",
      "ちがお",
      "ちが",
      "ちがう"
    ],
    "answer": 3,
    "correct": ""
  },
  {
    "idx": 17,
    "id": "n5-vocab_reading-017",
    "target": "大丈夫",
    "sentence": "この《大丈夫》の読み方を選んでください。",
    "options": [
      "だいじょうぶ",
      "だいじょぶ",
      "だいしょうぶ",
      "だいじょうぶい"
    ],
    "answer": 0,
    "correct": ""
  },
  {
    "idx": 18,
    "id": "n5-vocab_reading-018",
    "target": "誕生日",
    "sentence": "この《誕生日》の読み方を選んでください。",
    "options": [
      "たんじょうびい",
      "たんじょうび",
      "たんじょび",
      "たんしょうび"
    ],
    "answer": 1,
    "correct": ""
  },
  {
    "idx": 19,
    "id": "n5-vocab_reading-019",
    "target": "卵",
    "sentence": "この《卵》の読み方を選んでください。",
    "options": [
      "たまご",
      "たまごい",
      "たまお"
    ],
    "answer": 0,
    "correct": ""
  },
  {
    "idx": 20,
    "id": "n5-vocab_reading-020",
    "target": "丁度",
    "sentence": "この《丁度》の読み方を選んでください。",
    "options": [
      "ちょうどい",
      "ちょど",
      "ちょうど",
      "ちょうお"
    ],
    "answer": 2,
    "correct": ""
  },
  {
    "idx": 21,
    "id": "n5-vocab_reading-021",
    "target": "小さい",
    "sentence": "この《小さい》の読み方を選んでください。",
    "options": [
      "ちいさい",
      "ちいさいい",
      "ちいさお"
    ],
    "answer": 0,
    "correct": ""
  },
  {
    "idx": 22,
    "id": "n5-vocab_reading-022",
    "target": "近く",
    "sentence": "この《近く》の読み方を選んでください。",
    "options": [
      "ちかく",
      "ちかくい",
      "ちかお"
    ],
    "answer": 0,
    "correct": ""
  },
  {
    "idx": 23,
    "id": "n5-vocab_reading-023",
    "target": "机",
    "sentence": "この《机》の読み方を選んでください。",
    "options": [
      "つくえい",
      "つくえ",
      "つくお"
    ],
    "answer": 1,
    "correct": ""
  },
  {
    "idx": 24,
    "id": "n5-vocab_reading-024",
    "target": "食べ物",
    "sentence": "この《食べ物》の読み方を選んでください。",
    "options": [
      "たべもお",
      "たべものい",
      "たべもの"
    ],
    "answer": 2,
    "correct": ""
  },
  {
    "idx": 25,
    "id": "n5-vocab_reading-025",
    "target": "出す",
    "sentence": "この《出す》の読み方を選んでください。",
    "options": [
      "だすい",
      "だす",
      "だお"
    ],
    "answer": 1,
    "correct": ""
  },
  {
    "idx": 26,
    "id": "n5-vocab_reading-026",
    "target": "切符",
    "sentence": "この《切符》の読み方を選んでください。",
    "options": [
      "きっお",
      "きっぷい",
      "きぷ",
      "きっぷ"
    ],
    "answer": 3,
    "correct": ""
  },
  {
    "idx": 27,
    "id": "n5-vocab_reading-027",
    "target": "お菓子",
    "sentence": "この《お菓子》の読み方を選んでください。",
    "options": [
      "おかお",
      "おかしい",
      "おかし"
    ],
    "answer": 2,
    "correct": ""
  },
  {
    "idx": 28,
    "id": "n5-vocab_reading-028",
    "target": "鞄",
    "sentence": "この《鞄》の読み方を選んでください。",
    "options": [
      "かばお",
      "かばんい",
      "かはん",
      "かばん"
    ],
    "answer": 3,
    "correct": ""
  },
  {
    "idx": 29,
    "id": "n5-vocab_reading-029",
    "target": "鉛筆",
    "sentence": "この《鉛筆》の読み方を選んでください。",
    "options": [
      "えんぴつ",
      "えんぴつい",
      "えんぴお"
    ],
    "answer": 0,
    "correct": ""
  },
  {
    "idx": 30,
    "id": "n5-vocab_reading-030",
    "target": "茶色",
    "sentence": "この《茶色》の読み方を選んでください。",
    "options": [
      "ちゃいお",
      "ちゃいろい",
      "ちゃいろ"
    ],
    "answer": 2,
    "correct": ""
  },
  {
    "idx": 31,
    "id": "n5-vocab_reading-031",
    "target": "高い",
    "sentence": "この《高い》の読み方を選んでください。",
    "options": [
      "たかい",
      "たかいい",
      "たかお"
    ],
    "answer": 0,
    "correct": ""
  },
  {
    "idx": 32,
    "id": "n5-vocab_reading-032",
    "target": "押す",
    "sentence": "この《押す》の読み方を選んでください。",
    "options": [
      "おお",
      "おすい",
      "おす"
    ],
    "answer": 2,
    "correct": ""
  },
  {
    "idx": 33,
    "id": "n5-vocab_reading-033",
    "target": "誰か",
    "sentence": "この《誰か》の読み方を選んでください。",
    "options": [
      "だれかい",
      "だれお",
      "だれか"
    ],
    "answer": 2,
    "correct": ""
  },
  {
    "idx": 34,
    "id": "n5-vocab_reading-034",
    "target": "伯母さん",
    "sentence": "この《伯母さん》の読み方を選んでください。",
    "options": [
      "おばさお",
      "おばさんい",
      "おはさん",
      "おばさん"
    ],
    "answer": 3,
    "correct": ""
  },
  {
    "idx": 35,
    "id": "n5-vocab_reading-035",
    "target": "大好き",
    "sentence": "この《大好き》の読み方を選んでください。",
    "options": [
      "だいすきい",
      "だいすお",
      "だいすき"
    ],
    "answer": 2,
    "correct": ""
  },
  {
    "idx": 36,
    "id": "n5-vocab_reading-036",
    "target": "泳ぐ",
    "sentence": "この《泳ぐ》の読み方を選んでください。",
    "options": [
      "およぐい",
      "およぐ",
      "およお"
    ],
    "answer": 1,
    "correct": ""
  },
  {
    "idx": 37,
    "id": "n5-vocab_reading-037",
    "target": "女",
    "sentence": "この《女》の読み方を選んでください。",
    "options": [
      "おんな",
      "おんない",
      "おんお"
    ],
    "answer": 0,
    "correct": ""
  },
  {
    "idx": 38,
    "id": "n5-vocab_reading-038",
    "target": "疲れる",
    "sentence": "この《疲れる》の読み方を選んでください。",
    "options": [
      "つかれお",
      "つかれるい",
      "つかれる"
    ],
    "answer": 2,
    "correct": ""
  },
  {
    "idx": 39,
    "id": "n5-vocab_reading-039",
    "target": "覚える",
    "sentence": "この《覚える》の読み方を選んでください。",
    "options": [
      "おぼえる",
      "おぼえるい",
      "おぼえお"
    ],
    "answer": 0,
    "correct": ""
  },
  {
    "idx": 40,
    "id": "n5-vocab_reading-040",
    "target": "お酒",
    "sentence": "この《お酒》の読み方を選んでください。",
    "options": [
      "おさけ",
      "おさけい",
      "おさお"
    ],
    "answer": 0,
    "correct": ""
  },
  {
    "idx": 41,
    "id": "n5-vocab_reading-041",
    "target": "お兄さん",
    "sentence": "この《お兄さん》の読み方を選んでください。",
    "options": [
      "おにいさお",
      "おにいさんい",
      "おにいさん"
    ],
    "answer": 2,
    "correct": ""
  },
  {
    "idx": 42,
    "id": "n5-vocab_reading-042",
    "target": "音楽",
    "sentence": "この《音楽》の読み方を選んでください。",
    "options": [
      "おんがく",
      "おんがくい",
      "おんがお"
    ],
    "answer": 0,
    "correct": ""
  },
  {
    "idx": 43,
    "id": "n5-vocab_reading-043",
    "target": "弟",
    "sentence": "この《弟》の読み方を選んでください。",
    "options": [
      "おとうお",
      "おとと",
      "おとうとい",
      "おとうと"
    ],
    "answer": 3,
    "correct": ""
  },
  {
    "idx": 44,
    "id": "n5-vocab_reading-044",
    "target": "今",
    "sentence": "この《今》の読み方を選んでください。",
    "options": [
      "いまい",
      "いま",
      "いお"
    ],
    "answer": 1,
    "correct": ""
  },
  {
    "idx": 45,
    "id": "n5-vocab_reading-045",
    "target": "大切",
    "sentence": "この《大切》の読み方を選んでください。",
    "options": [
      "たいせお",
      "たいせつい",
      "たいせつ"
    ],
    "answer": 2,
    "correct": ""
  },
  {
    "idx": 46,
    "id": "n5-vocab_reading-046",
    "target": "楽しい",
    "sentence": "この《楽しい》の読み方を選んでください。",
    "options": [
      "たのしい",
      "たのしいい",
      "たのしお"
    ],
    "answer": 0,
    "correct": ""
  },
  {
    "idx": 47,
    "id": "n5-vocab_reading-047",
    "target": "嫌",
    "sentence": "この《嫌》の読み方を選んでください。",
    "options": [
      "いや",
      "いやい",
      "いお"
    ],
    "answer": 0,
    "correct": ""
  },
  {
    "idx": 48,
    "id": "n5-vocab_reading-048",
    "target": "次",
    "sentence": "この《次》の読み方を選んでください。",
    "options": [
      "つお",
      "つぎい",
      "つぎ"
    ],
    "answer": 2,
    "correct": ""
  },
  {
    "idx": 49,
    "id": "n5-vocab_reading-049",
    "target": "歩く",
    "sentence": "この《歩く》の読み方を選んでください。",
    "options": [
      "あるお",
      "あるくい",
      "あるく"
    ],
    "answer": 2,
    "correct": ""
  },
  {
    "idx": 50,
    "id": "n5-vocab_reading-050",
    "target": "有る",
    "sentence": "この《有る》の読み方を選んでください。",
    "options": [
      "あお",
      "ある",
      "あるい"
    ],
    "answer": 1,
    "correct": ""
  },
  {
    "idx": 51,
    "id": "n5-vocab_reading-051",
    "target": "体",
    "sentence": "この《体》の読み方を選んでください。",
    "options": [
      "からだい",
      "からお",
      "からだ"
    ],
    "answer": 2,
    "correct": ""
  },
  {
    "idx": 52,
    "id": "n5-vocab_reading-052",
    "target": "青",
    "sentence": "この《青》の読み方を選んでください。",
    "options": [
      "あお",
      "あおい"
    ],
    "answer": 0,
    "correct": ""
  },
  {
    "idx": 53,
    "id": "n5-vocab_reading-053",
    "target": "一昨年",
    "sentence": "この《一昨年》の読み方を選んでください。",
    "options": [
      "おととし",
      "おととお",
      "おととしい"
    ],
    "answer": 0,
    "correct": ""
  },
  {
    "idx": 54,
    "id": "n5-vocab_reading-054",
    "target": "立つ",
    "sentence": "この《立つ》の読み方を選んでください。",
    "options": [
      "たつ",
      "たお",
      "たつい"
    ],
    "answer": 0,
    "correct": ""
  },
  {
    "idx": 55,
    "id": "n5-vocab_reading-055",
    "target": "赤",
    "sentence": "この《赤》の読み方を選んでください。",
    "options": [
      "あかい",
      "あか",
      "あお"
    ],
    "answer": 1,
    "correct": ""
  },
  {
    "idx": 56,
    "id": "n5-vocab_reading-056",
    "target": "縦",
    "sentence": "この《縦》の読み方を選んでください。",
    "options": [
      "たてい",
      "たて",
      "たお"
    ],
    "answer": 1,
    "correct": ""
  },
  {
    "idx": 57,
    "id": "n5-vocab_reading-057",
    "target": "朝御飯",
    "sentence": "この《朝御飯》の読み方を選んでください。",
    "options": [
      "あさごはん",
      "あさごはんい",
      "あさごはお"
    ],
    "answer": 0,
    "correct": ""
  },
  {
    "idx": 58,
    "id": "n5-vocab_reading-058",
    "target": "多分",
    "sentence": "この《多分》の読み方を選んでください。",
    "options": [
      "たぶお",
      "たぶんい",
      "たぶん"
    ],
    "answer": 2,
    "correct": ""
  },
  {
    "idx": 59,
    "id": "n5-vocab_reading-059",
    "target": "階段",
    "sentence": "この《階段》の読み方を選んでください。",
    "options": [
      "かいだんい",
      "かいだん",
      "かいだお"
    ],
    "answer": 1,
    "correct": ""
  },
  {
    "idx": 60,
    "id": "n5-vocab_reading-060",
    "target": "誰",
    "sentence": "この《誰》の読み方を選んでください。",
    "options": [
      "だれ",
      "だれい",
      "だお"
    ],
    "answer": 0,
    "correct": ""
  },
  {
    "idx": 61,
    "id": "n5-vocab_reading-061",
    "target": "明日",
    "sentence": "この《明日》の読み方を選んでください。",
    "options": [
      "あしお",
      "あしたい",
      "あした"
    ],
    "answer": 2,
    "correct": ""
  },
  {
    "idx": 62,
    "id": "n5-vocab_reading-062",
    "target": "居る",
    "sentence": "この《居る》の読み方を選んでください。",
    "options": [
      "いる",
      "いるい",
      "いお"
    ],
    "answer": 0,
    "correct": ""
  },
  {
    "idx": 63,
    "id": "n5-vocab_reading-063",
    "target": "建物",
    "sentence": "この《建物》の読み方を選んでください。",
    "options": [
      "たてもお",
      "たてものい",
      "たてもの"
    ],
    "answer": 2,
    "correct": ""
  },
  {
    "idx": 64,
    "id": "n5-vocab_reading-064",
    "target": "借りる",
    "sentence": "この《借りる》の読み方を選んでください。",
    "options": [
      "かりお",
      "かりるい",
      "かりる"
    ],
    "answer": 2,
    "correct": ""
  },
  {
    "idx": 65,
    "id": "n5-vocab_reading-065",
    "target": "地下鉄",
    "sentence": "この《地下鉄》の読み方を選んでください。",
    "options": [
      "ちかてつ",
      "ちかてつい",
      "ちかてお"
    ],
    "answer": 0,
    "correct": ""
  },
  {
    "idx": 66,
    "id": "n5-vocab_reading-066",
    "target": "姉",
    "sentence": "この《姉》の読み方を選んでください。",
    "options": [
      "あね",
      "あお",
      "あねい"
    ],
    "answer": 0,
    "correct": ""
  },
  {
    "idx": 67,
    "id": "n5-vocab_reading-067",
    "target": "大変",
    "sentence": "この《大変》の読み方を選んでください。",
    "options": [
      "たいへお",
      "たいへんい",
      "たいへん"
    ],
    "answer": 2,
    "correct": ""
  },
  {
    "idx": 68,
    "id": "n5-vocab_reading-068",
    "target": "果物",
    "sentence": "この《果物》の読み方を選んでください。",
    "options": [
      "くだものい",
      "くだもの",
      "くだもお"
    ],
    "answer": 1,
    "correct": ""
  },
  {
    "idx": 69,
    "id": "n5-vocab_reading-069",
    "target": "食べる",
    "sentence": "この《食べる》の読み方を選んでください。",
    "options": [
      "たべる",
      "たべるい",
      "たべお"
    ],
    "answer": 0,
    "correct": ""
  },
  {
    "idx": 70,
    "id": "n5-vocab_reading-070",
    "target": "一日",
    "sentence": "この《一日》の読み方を選んでください。",
    "options": [
      "ついたち",
      "ついたちい",
      "ついたお"
    ],
    "answer": 0,
    "correct": ""
  },
  {
    "idx": 71,
    "id": "n5-vocab_reading-071",
    "target": "近い",
    "sentence": "この《近い》の読み方を選んでください。",
    "options": [
      "ちかお",
      "ちかいい",
      "ちかい"
    ],
    "answer": 2,
    "correct": ""
  },
  {
    "idx": 72,
    "id": "n5-vocab_reading-072",
    "target": "河",
    "sentence": "この《河》の読み方を選んでください。",
    "options": [
      "かわ",
      "かお",
      "かわい"
    ],
    "answer": 0,
    "correct": ""
  },
  {
    "idx": 73,
    "id": "n5-vocab_reading-073",
    "target": "暑い",
    "sentence": "この《暑い》の読み方を選んでください。",
    "options": [
      "あつお",
      "あついい",
      "あつい"
    ],
    "answer": 2,
    "correct": ""
  },
  {
    "idx": 74,
    "id": "n5-vocab_reading-074",
    "target": "地図",
    "sentence": "この《地図》の読み方を選んでください。",
    "options": [
      "ちお",
      "ちずい",
      "ちず"
    ],
    "answer": 2,
    "correct": ""
  },
  {
    "idx": 75,
    "id": "n5-vocab_reading-075",
    "target": "火曜日",
    "sentence": "この《火曜日》の読み方を選んでください。",
    "options": [
      "かようびい",
      "かようび",
      "かよび",
      "かようお"
    ],
    "answer": 1,
    "correct": ""
  },
  {
    "idx": 76,
    "id": "n5-vocab_reading-076",
    "target": "背広",
    "sentence": "この《背広》の読み方を選んでください。",
    "options": [
      "せびろい",
      "せびろ",
      "せびお"
    ],
    "answer": 1,
    "correct": ""
  },
  {
    "idx": 77,
    "id": "n5-vocab_reading-077",
    "target": "雑誌",
    "sentence": "この《雑誌》の読み方を選んでください。",
    "options": [
      "ざっし",
      "ざし",
      "ざっお",
      "ざっしい"
    ],
    "answer": 0,
    "correct": ""
  },
  {
    "idx": 78,
    "id": "n5-vocab_reading-078",
    "target": "然し",
    "sentence": "この《然し》の読み方を選んでください。",
    "options": [
      "しかお",
      "しかしい",
      "しかし"
    ],
    "answer": 2,
    "correct": ""
  },
  {
    "idx": 79,
    "id": "n5-vocab_reading-079",
    "target": "結婚",
    "sentence": "この《結婚》の読み方を選んでください。",
    "options": [
      "けっこん",
      "けっこお",
      "けこん",
      "けっこんい"
    ],
    "answer": 0,
    "correct": ""
  },
  {
    "idx": 80,
    "id": "n5-vocab_reading-080",
    "target": "声",
    "sentence": "この《声》の読み方を選んでください。",
    "options": [
      "こえ",
      "こえい",
      "こお"
    ],
    "answer": 0,
    "correct": ""
  },
  {
    "idx": 81,
    "id": "n5-vocab_reading-081",
    "target": "一",
    "sentence": "この《一》の読み方を選んでください。",
    "options": [
      "いち",
      "いちい",
      "いお"
    ],
    "answer": 0,
    "correct": ""
  },
  {
    "idx": 82,
    "id": "n5-vocab_reading-082",
    "target": "台所",
    "sentence": "この《台所》の読み方を選んでください。",
    "options": [
      "だいどころ",
      "だいどころい",
      "だいどこお"
    ],
    "answer": 0,
    "correct": ""
  },
  {
    "idx": 83,
    "id": "n5-vocab_reading-083",
    "target": "後",
    "sentence": "この《後》の読み方を選んでください。",
    "options": [
      "あお",
      "あと",
      "あとい"
    ],
    "answer": 1,
    "correct": ""
  },
  {
    "idx": 84,
    "id": "n5-vocab_reading-084",
    "target": "甘い",
    "sentence": "この《甘い》の読み方を選んでください。",
    "options": [
      "あまお",
      "あまいい",
      "あまい"
    ],
    "answer": 2,
    "correct": ""
  },
  {
    "idx": 85,
    "id": "n5-vocab_reading-085",
    "target": "曇り",
    "sentence": "この《曇り》の読み方を選んでください。",
    "options": [
      "くもお",
      "くもりい",
      "くもり"
    ],
    "answer": 2,
    "correct": ""
  },
  {
    "idx": 86,
    "id": "n5-vocab_reading-086",
    "target": "使う",
    "sentence": "この《使う》の読み方を選んでください。",
    "options": [
      "つかう",
      "つか",
      "つかうい",
      "つかお"
    ],
    "answer": 0,
    "correct": ""
  },
  {
    "idx": 87,
    "id": "n5-vocab_reading-087",
    "target": "友達",
    "sentence": "この《友達》の読み方を選んでください。",
    "options": [
      "ともだちい",
      "ともだち",
      "ともだお"
    ],
    "answer": 1,
    "correct": ""
  },
  {
    "idx": 88,
    "id": "n5-vocab_reading-088",
    "target": "切手",
    "sentence": "この《切手》の読み方を選んでください。",
    "options": [
      "きってい",
      "きっお",
      "きって",
      "きて"
    ],
    "answer": 2,
    "correct": ""
  },
  {
    "idx": 89,
    "id": "n5-vocab_reading-089",
    "target": "年",
    "sentence": "この《年》の読み方を選んでください。",
    "options": [
      "とし",
      "とお",
      "としい"
    ],
    "answer": 0,
    "correct": ""
  },
  {
    "idx": 90,
    "id": "n5-vocab_reading-090",
    "target": "閉まる",
    "sentence": "この《閉まる》の読み方を選んでください。",
    "options": [
      "しまる",
      "しまるい",
      "しまお"
    ],
    "answer": 0,
    "correct": ""
  },
  {
    "idx": 91,
    "id": "n5-vocab_reading-091",
    "target": "所",
    "sentence": "この《所》の読み方を選んでください。",
    "options": [
      "とこお",
      "ところい",
      "ところ"
    ],
    "answer": 2,
    "correct": ""
  },
  {
    "idx": 92,
    "id": "n5-vocab_reading-092",
    "target": "上着",
    "sentence": "この《上着》の読み方を選んでください。",
    "options": [
      "わぎ",
      "うわぎい",
      "うわお",
      "うわぎ"
    ],
    "answer": 3,
    "correct": ""
  },
  {
    "idx": 93,
    "id": "n5-vocab_reading-093",
    "target": "お弁当",
    "sentence": "この《お弁当》の読み方を選んでください。",
    "options": [
      "おべんと",
      "おべんとう",
      "おべんとお",
      "おべんとうい"
    ],
    "answer": 1,
    "correct": ""
  },
  {
    "idx": 94,
    "id": "n5-vocab_reading-094",
    "target": "賑やか",
    "sentence": "この《賑やか》の読み方を選んでください。",
    "options": [
      "にぎやかい",
      "にぎやか",
      "にぎやお"
    ],
    "answer": 1,
    "correct": ""
  },
  {
    "idx": 95,
    "id": "n5-vocab_reading-095",
    "target": "上げる",
    "sentence": "この《上げる》の読み方を選んでください。",
    "options": [
      "あげるい",
      "あげる",
      "あげお"
    ],
    "answer": 1,
    "correct": ""
  },
  {
    "idx": 96,
    "id": "n5-vocab_reading-096",
    "target": "中",
    "sentence": "この《中》の読み方を選んでください。",
    "options": [
      "なか",
      "なかい",
      "なお"
    ],
    "answer": 0,
    "correct": ""
  },
  {
    "idx": 97,
    "id": "n5-vocab_reading-097",
    "target": "警官",
    "sentence": "この《警官》の読み方を選んでください。",
    "options": [
      "けいかお",
      "けいかんい",
      "けいかん"
    ],
    "answer": 2,
    "correct": ""
  },
  {
    "idx": 98,
    "id": "n5-vocab_reading-098",
    "target": "習う",
    "sentence": "この《習う》の読み方を選んでください。",
    "options": [
      "ならう",
      "ならお",
      "ならうい",
      "なら"
    ],
    "answer": 0,
    "correct": ""
  },
  {
    "idx": 99,
    "id": "n5-vocab_reading-099",
    "target": "話す",
    "sentence": "この《話す》の読み方を選んでください。",
    "options": [
      "はなす",
      "はなすい",
      "はなお"
    ],
    "answer": 0,
    "correct": ""
  },
  {
    "idx": 100,
    "id": "n5-vocab_reading-100",
    "target": "とり肉",
    "sentence": "この《とり肉》の読み方を選んでください。",
    "options": [
      "とりにく",
      "とりにくい",
      "とりにお"
    ],
    "answer": 0,
    "correct": ""
  },
  {
    "idx": 101,
    "id": "n5-vocab_reading-101",
    "target": "電気",
    "sentence": "この《電気》の読み方を選んでください。",
    "options": [
      "でんお",
      "でんきい",
      "でんき"
    ],
    "answer": 2,
    "correct": ""
  },
  {
    "idx": 102,
    "id": "n5-vocab_reading-102",
    "target": "返す",
    "sentence": "この《返す》の読み方を選んでください。",
    "options": [
      "かえす",
      "かえすい",
      "かえお"
    ],
    "answer": 0,
    "correct": ""
  },
  {
    "idx": 103,
    "id": "n5-vocab_reading-103",
    "target": "半分",
    "sentence": "この《半分》の読み方を選んでください。",
    "options": [
      "はんぶんい",
      "はんぶん",
      "はんぶお"
    ],
    "answer": 1,
    "correct": ""
  },
  {
    "idx": 104,
    "id": "n5-vocab_reading-104",
    "target": "買う",
    "sentence": "この《買う》の読み方を選んでください。",
    "options": [
      "かう",
      "か",
      "かうい",
      "かお"
    ],
    "answer": 0,
    "correct": ""
  },
  {
    "idx": 105,
    "id": "n5-vocab_reading-105",
    "target": "教える",
    "sentence": "この《教える》の読み方を選んでください。",
    "options": [
      "おしえる",
      "おしえるい",
      "おしえお"
    ],
    "answer": 0,
    "correct": ""
  },
  {
    "idx": 106,
    "id": "n5-vocab_reading-106",
    "target": "東",
    "sentence": "この《東》の読み方を選んでください。",
    "options": [
      "ひがし",
      "ひがしい",
      "ひがお"
    ],
    "answer": 0,
    "correct": ""
  },
  {
    "idx": 107,
    "id": "n5-vocab_reading-107",
    "target": "肉",
    "sentence": "この《肉》の読み方を選んでください。",
    "options": [
      "にお",
      "にくい",
      "にく"
    ],
    "answer": 2,
    "correct": ""
  },
  {
    "idx": 108,
    "id": "n5-vocab_reading-108",
    "target": "作る",
    "sentence": "この《作る》の読み方を選んでください。",
    "options": [
      "つくる",
      "つくるい",
      "つくお"
    ],
    "answer": 0,
    "correct": ""
  },
  {
    "idx": 109,
    "id": "n5-vocab_reading-109",
    "target": "昨夜",
    "sentence": "この《昨夜》の読み方を選んでください。",
    "options": [
      "ゆうべ",
      "ゆべ",
      "ゆうべい",
      "ゆうお"
    ],
    "answer": 0,
    "correct": ""
  },
  {
    "idx": 110,
    "id": "n5-vocab_reading-110",
    "target": "奥さん",
    "sentence": "この《奥さん》の読み方を選んでください。",
    "options": [
      "おくさん",
      "おくさんい",
      "おくさお"
    ],
    "answer": 0,
    "correct": ""
  }
]