{
  "n2-vocab_reading-0828": "この湖の水は《透き通る》ように美しく、底まで見える。",
  "n2-vocab_reading-0829": "数学の授業でさまざまな《図形》の面積を求める問題を解いた。",
  "n2-vocab_reading-0830": "玄関に風鈴のような小さな《鈴》を飾っている。",
  "n2-vocab_reading-0832": "まだ使えるものを簡単に《棄てる》のはもったいない。",
  "n2-vocab_reading-0833": "彼女は先生のアドバイスを《素直》に受け入れて努力した。",
  "n2-vocab_reading-0834": "新しい《住まい》は駅から徒歩十分の便利な場所にある。",
  "n2-vocab_reading-0835": "冬の夜空は空気が《澄む》ため、星がひときわ美しく見える。",
  "n2-vocab_reading-0837": "あの手は少し《狡い》のではないかと皆が思っている。",
  "n2-vocab_reading-0838": "海外旅行から帰国する際は《税関》で荷物の検査を受ける。",
  "n2-vocab_reading-0839": "この映画の《製作》には五年もの歳月と巨額の予算がかかった。",
  "n2-vocab_reading-0840": "彼は若い頃から舞台作品の《制作》に携わってきた。",
  "n2-vocab_reading-0841": "この薬は水に溶けやすいという《性質》を持っている。",
  "n2-vocab_reading-0842": "レポートの下書きが完成したので明朝《清書》するつもりだ。",
  "n2-vocab_reading-0844": "この数学の問題では《整数》の範囲で答えを求めなさい。",
  "n2-vocab_reading-0846": "遭難者が厳しい状況下で七日間《生存》していたことが確認された。",
  "n2-vocab_reading-0847": "この地域の温暖な気候は稲の《生長》に適している。",
  "n2-vocab_reading-0848": "各《政党》の政策内容を比較してから投票先を決めようと思う。",
  "n2-vocab_reading-0849": "申込書の所定欄に氏名と《生年月日》を記入してください。",
  "n2-vocab_reading-0850": "車の定期的な《整備》は安全運転を確保するために欠かせない。",
  "n2-vocab_reading-0851": "食品を選ぶときは栄養《成分》表示を必ず確認する。",
  "n2-vocab_reading-0852": "《性別》に関係なく能力を正当に評価すべきだ。",
  "n2-vocab_reading-0854": "学校の《正門》前に集まった生徒たちが一斉に校舎へ向かった。",
  "n2-vocab_reading-0855": "日本では《西暦》のほかに元号も日常的に使われている。",
  "n2-vocab_reading-0856": "彼はプロジェクトリーダーとして大きな責任を《背負う》ことになった。",
  "n2-vocab_reading-0857": "《折角》招待したのに彼はどうしても都合がつかなかったらしい。",
  "n2-vocab_reading-0858": "大型の台風が日本列島に《接近》しているため注意が必要だ。",
  "n2-vocab_reading-0859": "彼は年齢に関係なく誰にでも丁寧に《接する》ことで知られている。",
  "n2-vocab_reading-0860": "プリンターをパソコンに正しく《接続》してから印刷を開始してください。",
  "n2-vocab_reading-0861": "この《瀬戸物》の湯呑みは職人が一つ一つ丁寧に仕上げている。",
  "n2-vocab_reading-0862": "敵陣を《攻める》前に十分な情報収集と準備が必要だ。"
}
