{
  "n2-vocab_reading-0794": "この教科書は日本語《初級》学習者向けに作られている。",
  "n2-vocab_reading-0795": "田中《助教授》の講義は専門的でとても勉強になる。",
  "n2-vocab_reading-0797": "彼はガラス細工の《職人》として国内外で高く評価されている。",
  "n2-vocab_reading-0798": "毎年六月《初旬》にこの地域では梅雨入りする。",
  "n2-vocab_reading-0799": "結婚祝いに上質な《食器》セットを友人からいただいた。",
  "n2-vocab_reading-0800": "駅ビルの三階にある《書店》で参考書を探した。",
  "n2-vocab_reading-0801": "祖母は週に一度《書道》教室に通っている。",
  "n2-vocab_reading-0802": "三十代に入った途端、《白髪》が気になり始めた。",
  "n2-vocab_reading-0803": "留学先でできた《知合い》と今でも連絡を取り合っている。",
  "n2-vocab_reading-0805": "鍋の《汁》が煮詰まらないように火加減に注意する。",
  "n2-vocab_reading-0806": "自分の可能性を《信ずる》ことが成功への第一歩だ。",
  "n2-vocab_reading-0807": "十分な睡眠は《心身》の疲れを回復するために欠かせない。",
  "n2-vocab_reading-0809": "年に一度は健康《診断》を受けるようにしている。",
  "n2-vocab_reading-0810": "災害時には《人命》救助が何よりも優先される。",
  "n2-vocab_reading-0811": "《深夜》まで及んだ会議はようやく終了した。",
  "n2-vocab_reading-0812": "この地域の《森林》は貴重な生態系を守るために保護されている。",
  "n2-vocab_reading-0813": "日本《神話》に登場する神々の物語は現代にも影響を与えている。",
  "n2-vocab_reading-0814": "《酢》には食欲を促進し疲労を回復する効果があると言われている。",
  "n2-vocab_reading-0815": "キャンプ場では当番制で《炊事》を担当することになった。",
  "n2-vocab_reading-0816": "温泉から立ち上る《水蒸気》で辺り一面が白く見える。",
  "n2-vocab_reading-0817": "《水素》は燃焼しても二酸化炭素を排出しないクリーンなエネルギーだ。",
  "n2-vocab_reading-0818": "このビルの壁は完全に《垂直》に建設されている。",
  "n2-vocab_reading-0819": "雨上がりの葉っぱに《水滴》がきらめいている。",
  "n2-vocab_reading-0820": "夏場の外出には必ず《水筒》を持参するようにしている。",
  "n2-vocab_reading-0822": "棚の高さが《水平》かどうか確認するために水準器を使った。",
  "n2-vocab_reading-0823": "夕日が《水平線》の彼方に沈む瞬間はとても美しい。",
  "n2-vocab_reading-0824": "この美術館は毎週《水曜》が休館日なので注意が必要だ。",
  "n2-vocab_reading-0825": "子供の頃、宇宙《図鑑》を何度も読み返した思い出がある。",
  "n2-vocab_reading-0826": "裏山には樹齢百年を超える《杉》の木が何本も立っている。",
  "n2-vocab_reading-0827": "彼は食べ物の《好き嫌い》が激しくて周りを困らせることがある。"
}
